Adafruit_PureIO/smbus.py
Adafruit_PureIO/__init__.py
Adafruit_PureIO-0.2.1.dist-info/metadata.json
Adafruit_PureIO-0.2.1.dist-info/METADATA
Adafruit_PureIO-0.2.1.dist-info/RECORD
Adafruit_PureIO-0.2.1.dist-info/WHEEL
Adafruit_PureIO-0.2.1.dist-info/DESCRIPTION.rst
Adafruit_PureIO-0.2.1.dist-info/top_level.txt
